odoo/addons/base_rest_pydantic/README.rst
odoo/addons/base_rest_pydantic/__init__.py
odoo/addons/base_rest_pydantic/__manifest__.py
odoo/addons/base_rest_pydantic/restapi.py
odoo/addons/base_rest_pydantic/i18n/base_rest_datamodel.pot
odoo/addons/base_rest_pydantic/i18n/base_rest_pydantic.pot
odoo/addons/base_rest_pydantic/i18n/it.po
odoo/addons/base_rest_pydantic/readme/CONTRIBUTORS.md
odoo/addons/base_rest_pydantic/readme/DESCRIPTION.md
odoo/addons/base_rest_pydantic/readme/USAGE.md
odoo/addons/base_rest_pydantic/static/description/icon.png
odoo/addons/base_rest_pydantic/static/description/index.html
odoo/addons/base_rest_pydantic/tests/__init__.py
odoo/addons/base_rest_pydantic/tests/test_from_params.py
odoo/addons/base_rest_pydantic/tests/test_response.py
odoo_addon_base_rest_pydantic-18.0.1.0.2.1.dist-info/METADATA
odoo_addon_base_rest_pydantic-18.0.1.0.2.1.dist-info/WHEEL
odoo_addon_base_rest_pydantic-18.0.1.0.2.1.dist-info/top_level.txt
odoo_addon_base_rest_pydantic-18.0.1.0.2.1.dist-info/RECORD
