Metadata-Version: 2.1
Name: odoo-addon-base_rest_pydantic
Version: 18.0.1.0.2.1
Requires-Python: >=3.10
Requires-Dist: odoo-addon-base_rest==18.0.*
Requires-Dist: odoo==18.0.*
Requires-Dist: pydantic>=2.0.0
Summary: Pydantic binding for base_rest
Home-page: https://github.com/OCA/rest-framework
License: LGPL-3
Author: ACSONE SA/NV,Odoo Community Association (OCA)
Author-email: support@odoo-community.org
Classifier: Programming Language :: Python
Classifier: Framework :: Odoo
Classifier: Framework :: Odoo :: 18.0
Classifier: License :: OSI Approved :: GNU Lesser General Public License v3 (LGPLv3)
